Workbook

Sheet Supuestos
A1: FRIKIDEX · Supuestos del modelo de FrikiTokens
A2: Edita solo las celdas en azul (las amarillas son las más importantes). Todo lo demás se calcula solo.
A4: General
A5: Tipo de cambio (MXN por USD) | B5: 19 | C5: Referencia aproximada; actualízalo al tipo de cambio del día.
A6: Comisión de la tienda (Apple/Google) | B6: 0.15 | C6: 15% con programa de pequeños desarrolladores; 30% si no aplica. Se calcula sobre el precio sin IVA.
A7: IVA | B7: 0.16 | C7: El precio de venta al público se asume con IVA incluido.
A8: Precios de Gemini (USD por millón de tokens, tarifa 2027)
A9: Gemini 3.8 Flash · entrada | B9: 1.5 | C9: ai.google.dev/gemini-api/docs/pricing — $0.75 hasta el 31-dic-2026, $1.50 desde el 1-ene-2027.
A10: Gemini 3.8 Flash · salida (incluye razonamiento) | B10: 7.5 | C10: Misma fuente — $3.75 hasta el 31-dic-2026, $7.50 desde el 1-ene-2027.
A11: Gemini 3.5 Flash-Lite · entrada | B11: 0.3 | C11: Misma fuente.
A12: Gemini 3.5 Flash-Lite · salida | B12: 2.5 | C12: Misma fuente.
A13: Búsqueda web (grounding), USD por búsqueda | B13: 0.014 | C13: Misma fuente — $14 por 1,000 búsquedas tras 5,000 gratis al mes (el modelo NO descuenta las gratis: escenario conservador).
A14: Búsquedas de Google por consulta de precio | B14: 2 | C14: Supuesto: una consulta puede disparar varias búsquedas y cada una se cobra.
A15: Tokens estimados por acción
A16: Escaneo "¿Ya lo tengo?" · tokens de entrada | B16: 2000 | C16: Foto (~1,100) + instrucciones. Supuesto a validar con pruebas reales.
A17: Escaneo "¿Ya lo tengo?" · tokens de salida | B17: 600 | C17: Respuesta corta, sin razonamiento extendido.
A18: Análisis completo · tokens de entrada | B18: 2000 | C18: Supuesto.
A19: Análisis completo · tokens de salida | B19: 1600 | C19: Ficha JSON + razonamiento en nivel bajo. Supuesto.
A20: Precio de mercado · tokens de entrada | B20: 800 | C20: Sin foto, solo datos del objeto. Supuesto.
A21: Precio de mercado · tokens de salida | B21: 600 | C21: Supuesto.
A22: FrikiTokens que cobra cada acción
A23: Escaneo "¿Ya lo tengo?" | B23: 1 | C23: Propuesta.
A24: Análisis completo (alta con IA) | B24: 2 | C24: Propuesta.
A25: Actualización / re-análisis | B25: 2 | C25: Propuesta.
A26: Precio de mercado | B26: 5 | C26: Propuesta.
A27: Mezcla de uso (de cada 100 acciones con IA)
A28: Escaneos "¿Ya lo tengo?" | B28: 50 | C28: Supuesto de comportamiento; ajústalo con datos reales.
A29: Análisis completos | B29: 30 | C29: Supuesto.
A30: Actualizaciones | B30: 10 | C30: Supuesto.
A31: Consultas de precio de mercado | B31: 10 | C31: Supuesto.

Sheet Costo por acción
A1: Costo real de cada acción con IA
A3: Acción | B3: Modelo | C3: Tokens entrada | D3: Tokens salida | E3: Costo IA (USD) | F3: Búsquedas web (USD) | G3: Costo total (USD) | H3: Costo total (MXN) | I3: FrikiTokens que cobra | J3: Costo real por FrikiToken (MXN)
A4: Escaneo "¿Ya lo tengo?" | B4: 3.5 Flash-Lite | C4: =Supuestos!$B$16 -> 2000 | D4: =Supuestos!$B$17 -> 600 | E4: =C4*Supuestos!$B$11/1000000+D4*Supuestos!$B$12/1000000 -> 0.0021 | F4: 0 | G4: =E4+F4 -> 0.0021 | H4: =G4*Supuestos!$B$5 -> 0.0399 | I4: =Supuestos!$B$23 -> 1 | J4: =IF(I4=0,0,H4/I4) -> 0.0399
A5: Análisis completo (alta con IA) | B5: 3.8 Flash | C5: =Supuestos!$B$18 -> 2000 | D5: =Supuestos!$B$19 -> 1600 | E5: =C5*Supuestos!$B$9/1000000+D5*Supuestos!$B$10/1000000 -> 0.015 | F5: 0 | G5: =E5+F5 -> 0.015 | H5: =G5*Supuestos!$B$5 -> 0.285 | I5: =Supuestos!$B$24 -> 2 | J5: =IF(I5=0,0,H5/I5) -> 0.1425
A6: Actualización / re-análisis | B6: 3.8 Flash | C6: =Supuestos!$B$18 -> 2000 | D6: =Supuestos!$B$19 -> 1600 | E6: =C6*Supuestos!$B$9/1000000+D6*Supuestos!$B$10/1000000 -> 0.015 | F6: 0 | G6: =E6+F6 -> 0.015 | H6: =G6*Supuestos!$B$5 -> 0.285 | I6: =Supuestos!$B$25 -> 2 | J6: =IF(I6=0,0,H6/I6) -> 0.1425
A7: Precio de mercado | B7: 3.8 Flash + búsqueda | C7: =Supuestos!$B$20 -> 800 | D7: =Supuestos!$B$21 -> 600 | E7: =C7*Supuestos!$B$9/1000000+D7*Supuestos!$B$10/1000000 -> 0.0057 | F7: =Supuestos!$B$13*Supuestos!$B$14 -> 0.028 | G7: =E7+F7 -> 0.0337 | H7: =G7*Supuestos!$B$5 -> 0.6403 | I7: =Supuestos!$B$26 -> 5 | J7: =IF(I7=0,0,H7/I7) -> 0.12806
A10: Costo real promedio por FrikiToken (según la mezcla de uso) | J10: =IF((Supuestos!$B$28*I4+Supuestos!$B$29*I5+Supuestos!$B$30*I6+Supuestos!$B$31*I7)=0,0,(Supuestos!$B$28*H4+Supuestos!$B$29*H5+Supuestos!$B$30*H6+Supuestos!$B$31*H7)/(Supuestos!$B$28*I4+Supuestos!$B$29*I5+Supuestos!$B$30*I6+Supuestos!$B$31*I7)) -> 0.10998889
A11: Es el número que usa la hoja "Paquetes" para calcular tu gasto. Cambia si modificas la mezcla de uso en Supuestos.

Sheet Paquetes
A1: Gasto vs venta vs ganancia por paquete de FrikiTokens
A2: Edita en azul el nombre, FrikiTokens y precio de cada paquete. Todo en MXN.
A4: Paquete | B4: FrikiTokens | C4: Precio al público (con IVA) | D4: Precio por FrikiToken | E4: IVA | F4: Comisión tienda | G4: Ingreso neto para ti | H4: Gasto en IA (si se usan todos) | I4: Ganancia | J4: Margen sobre precio | K4: Cuántas veces cubre el gasto
A5: Básico | B5: 100 | C5: 69 | D5: =IF(B5=0,0,C5/B5) -> 0.69 | E5: =C5-C5/(1+Supuestos!$B$7) -> 9.5172414 | F5: =(C5-E5)*Supuestos!$B$6 -> 8.9224138 | G5: =C5-E5-F5 -> 50.560345 | H5: =B5*'Costo por acción'!$J$10 -> 10.998889 | I5: =G5-H5 -> 39.561456 | J5: =IF(C5=0,0,I5/C5) -> 0.57335443 | K5: =IF(H5=0,0,G5/H5) -> 4.5968593
A6: Coleccionista | B6: 300 | C6: 179 | D6: =IF(B6=0,0,C6/B6) -> 0.59666667 | E6: =C6-C6/(1+Supuestos!$B$7) -> 24.689655 | F6: =(C6-E6)*Supuestos!$B$6 -> 23.146552 | G6: =C6-E6-F6 -> 131.16379 | H6: =B6*'Costo por acción'!$J$10 -> 32.996667 | I6: =G6-H6 -> 98.167126 | J6: =IF(C6=0,0,I6/C6) -> 0.5484197 | K6: =IF(H6=0,0,G6/H6) -> 3.9750619
A7: Mega | B7: 1000 | C7: 499 | D7: =IF(B7=0,0,C7/B7) -> 0.499 | E7: =C7-C7/(1+Supuestos!$B$7) -> 68.827586 | F7: =(C7-E7)*Supuestos!$B$6 -> 64.525862 | G7: =C7-E7-F7 -> 365.64655 | H7: =B7*'Costo por acción'!$J$10 -> 109.98889 | I7: =G7-H7 -> 255.65766 | J7: =IF(C7=0,0,I7/C7) -> 0.51234001 | K7: =IF(H7=0,0,G7/H7) -> 3.3243954
A9: Notas
A10: • "Gasto en IA" asume que el usuario gasta todos sus FrikiTokens. Los que no se usan son ganancia extra.
A11: • No incluye servidores, almacenamiento de fotos ni las 5,000 búsquedas gratis al mes de Google (escenario conservador).
A12: • La comisión de tienda solo aplica si vendes dentro de la app; en la web (Stripe) cambia por la comisión de Stripe.

Sheet Proyección mensual
A1: Proyección mensual: gasto vs venta vs ganancia
A2: Edita en azul cuántos usuarios hay y cuántos paquetes vendes al mes.
A4: Usuarios gratuitos activos | B4: 500
A5: FrikiTokens de regalo por usuario al mes | B5: 20
A6: % de los tokens de regalo que realmente se usan | B6: 0.6
A8: Paquete | B8: Paquetes vendidos al mes | C8: Venta total (con IVA) | D8: Ingreso neto | E8: Gasto en IA | F8: Ganancia
A9: =Paquetes!A5 -> Básico | B9: 40 | C9: =B9*Paquetes!C5 -> 2760 | D9: =B9*Paquetes!G5 -> 2022.4138 | E9: =B9*Paquetes!H5 -> 439.95556 | F9: =D9-E9 -> 1582.4582
A10: =Paquetes!A6 -> Coleccionista | B10: 15 | C10: =B10*Paquetes!C6 -> 2685 | D10: =B10*Paquetes!G6 -> 1967.4569 | E10: =B10*Paquetes!H6 -> 494.95 | F10: =D10-E10 -> 1472.5069
A11: =Paquetes!A7 -> Mega | B11: 5 | C11: =B11*Paquetes!C7 -> 2495 | D11: =B11*Paquetes!G7 -> 1828.2328 | E11: =B11*Paquetes!H7 -> 549.94444 | F11: =D11-E11 -> 1278.2883
A12: Costo de los tokens de regalo | E12: =B4*B5*B6*'Costo por acción'!$J$10 -> 659.93333 | F12: =-E12 -> -659.93333
A13: TOTAL DEL MES | B13: =SUM(B9:B11) -> 60 | C13: =SUM(C9:C11) -> 7940 | D13: =SUM(D9:D11) -> 5818.1034 | E13: =SUM(E9:E12) -> 2144.7833 | F13: =SUM(F9:F12) -> 3673.3201
A15: Margen del mes sobre la venta total | F15: =IF(C13=0,0,F13/C13) -> 0.46263478
